[
    {
        "name": "createdAt",
        "mode": "",
        "type": "DATETIME",
        "description": "",
        "fields": []
    },
    {
        "name": "description",
        "mode": "",
        "type": "STRING",
        "description": "",
        "fields": []
    },
    {
        "name": "id",
        "mode": "",
        "type": "INTEGER",
        "description": "",
        "fields": []
    },
    {
        "name": "order",
        "mode": "",
        "type": "INTEGER",
        "description": "",
        "fields": []
    },
    {
        "name": "pageId",
        "mode": "",
        "type": "INTEGER",
        "description": "",
        "fields": []
    },
    {
        "name": "questionTemplateId",
        "mode": "",
        "type": "INTEGER",
        "description": "",
        "fields": []
    },
    {
        "name": "updatedAt",
        "mode": "",
        "type": "DATETIME",
        "description": "",
        "fields": []
    }
]