[
    {
        "mode": "NULLABLE",
        "name": "TEG_DT_ATUALIZACAO",
        "type": "TIMESTAMP",
        "description": ""
    },
    {
        "mode": "NULLABLE",
        "name": "TEG_DT_CRIACAO",
        "type": "TIMESTAMP",
        "description": ""
    },
    {
        "mode": "NULLABLE",
        "name": "TEG_ID",
        "type": "INTEGER",
        "description": ""
    },
    {
        "mode": "NULLABLE",
        "name": "TEG_MTI_ID",
        "type": "INTEGER",
        "description": ""
    },
    {
        "mode": "NULLABLE",
        "name": "TEG_OLD_ID",
        "type": "INTEGER",
        "description": ""
    },
    {
        "mode": "NULLABLE",
        "name": "TEG_ORDEM",
        "type": "INTEGER",
        "description": ""
    },
    {
        "mode": "NULLABLE",
        "name": "TEG_RESPOSTA_CORRETA",
        "type": "STRING",
        "description": ""
    },
    {
        "mode": "NULLABLE",
        "name": "TEG_TES_ID",
        "type": "INTEGER",
        "description": ""
    }
]